zeroone/__init__.py
zeroone-0.0.1.dist-info/LICENSE
zeroone-0.0.1.dist-info/METADATA
zeroone-0.0.1.dist-info/WHEEL
zeroone-0.0.1.dist-info/top_level.txt
zeroone-0.0.1.dist-info/RECORD
