Metadata-Version: 2.1
Name: zeroone
Version: 0.0.1
Summary: Project ZeroOne
Home-page: https://github.com/tjbanks/ZeroOne
Author: Tyler Banks
Author-email: tbanks@mail.missouri.edu
License: MIT
Platform: UNKNOWN
Classifier: Intended Audience :: Developers
Classifier: Intended Audience :: Education
Classifier: Intended Audience :: Science/Research
Classifier: License :: OSI Approved :: MIT License
Classifier: Programming Language :: Python :: 3
Classifier: Programming Language :: Python :: 3.6
Classifier: Topic :: Software Development :: Libraries
Classifier: Topic :: Software Development :: Libraries :: Python Modules
Classifier: Operating System :: OS Independent
